json_ql/__init__.py
json_ql/driver.py
json_ql/json_ql_dict.py
json_ql/constants/__init__.py
json_ql/constants/regex_constants.py
json_ql/extracter/__init__.py
json_ql/extracter/data_extracter.py
json_ql/extracter/key_data_extracter.py
json_ql/extracter/list_data_extracter.py
json_ql/extracter/list_range_data_extracter.py
json_ql/extracter/object_list_data_extracter.py
json_ql/extracter/object_list_data_regex_extracter.py
test/__init__.py
test/test_json_ql/__init__.py
test/test_json_ql/test_extracter/__init__.py
test/test_json_ql/test_extracter/test_key_data_extracter.py
test/test_json_ql/test_extracter/test_list_data_extracter.py
json_ql-0.2.2.dist-info/LICENSE
json_ql-0.2.2.dist-info/METADATA
json_ql-0.2.2.dist-info/WHEEL
json_ql-0.2.2.dist-info/top_level.txt
json_ql-0.2.2.dist-info/RECORD
