Metadata-Version: 2.1
Name: json-ql
Version: 0.2.2
Summary: A query language for json
Home-page: https://github.com/Bharat23/json-ql
Author: Bharat Sinha
Author-email: bharat.sinha.2307@gmail.com
License: MIT
Keywords: json,query,lookup,dict,list,key
Classifier: Programming Language :: Python :: 3
Classifier: License :: OSI Approved :: MIT License
Classifier: Operating System :: OS Independent
Classifier: Intended Audience :: Developers
Requires-Python: >=3.6
License-File: LICENSE
